<?xml version="1.0" encoding="UTF-8"?>
<metadata xml:lang="en"><Esri><CreaDate>20251108</CreaDate><CreaTime>15321700</CreaTime><ArcGISFormat>1.0</ArcGISFormat><SyncOnce>TRUE</SyncOnce><DataProperties><lineage><Process ToolSource="c:\program files\arcgis\server\framework\runtime\arcgis\Resources\ArcToolbox\toolboxes\Data Management Tools.tbx\SetRasterProperties" Date="20251108" Time="153217">SetRasterProperties C:\Users\igskmncn-swscArc\AppData\Local\Temp\landfireproductservice_gpserver\jfadfe07902304d65bef91309b76fe1b5\scratch\jfadfe07902304d65bef91309b76fe1b5.tif Thematic # # # "Creator 'USGS EROS Landfire Product Service'" #</Process><Process ToolSource="c:\program files\arcgis\server\framework\runtime\arcgis\Resources\ArcToolbox\toolboxes\Data Management Tools.tbx\SetRasterProperties" Date="20251108" Time="153218">SetRasterProperties C:\Users\igskmncn-swscArc\AppData\Local\Temp\landfireproductservice_gpserver\jfadfe07902304d65bef91309b76fe1b5\scratch\jfadfe07902304d65bef91309b76fe1b5.tif # # # # "ResampleResolution 31" #</Process></lineage></DataProperties></Esri></metadata>
